py_zipkin/__init__.py
py_zipkin/exception.py
py_zipkin/logging_helper.py
py_zipkin/py.typed
py_zipkin/request_helpers.py
py_zipkin/storage.py
py_zipkin/thread_local.py
py_zipkin/transport.py
py_zipkin/util.py
py_zipkin/zipkin.py
py_zipkin/encoding/__init__.py
py_zipkin/encoding/_decoders.py
py_zipkin/encoding/_encoders.py
py_zipkin/encoding/_helpers.py
py_zipkin/encoding/_types.py
py_zipkin/encoding/protobuf/__init__.py
py_zipkin/encoding/protobuf/zipkin_pb2.py
py_zipkin/encoding/protobuf/zipkin_pb2.pyi
py_zipkin/instrumentations/__init__.py
py_zipkin/instrumentations/python_threads.py
py_zipkin/testing/__init__.py
py_zipkin/testing/mock_transport.py
py_zipkin-1.2.8.dist-info/LICENSE.txt
py_zipkin-1.2.8.dist-info/METADATA
py_zipkin-1.2.8.dist-info/WHEEL
py_zipkin-1.2.8.dist-info/top_level.txt
py_zipkin-1.2.8.dist-info/RECORD
