Metadata-Version: 2.1
Name: py-zipkin
Version: 1.2.8
Summary: Library for using Zipkin in Python.
Home-page: https://github.com/Yelp/py_zipkin
Author: Yelp, Inc.
Author-email: opensource+py-zipkin@yelp.com
License: Copyright Yelp 2019
Platform: UNKNOWN
Classifier: Development Status :: 3 - Alpha
Classifier: Intended Audience :: Developers
Classifier: Topic :: Software Development :: Libraries :: Python Modules
Classifier: License :: OSI Approved :: Apache Software License
Classifier: Operating System :: OS Independent
Classifier: Programming Language :: Python :: 3.7
Classifier: Programming Language :: Python :: 3.8
Provides: py_zipkin
Requires-Python: >=3.7
Provides-Extra: protobuf
